docs/source/conf.py
trplearn/__init__.py
trplearn/regression.py
trplearn/trpalg.py
trplearn-0.1.1.dist-info/LICENSE
trplearn-0.1.1.dist-info/METADATA
trplearn-0.1.1.dist-info/WHEEL
trplearn-0.1.1.dist-info/top_level.txt
trplearn-0.1.1.dist-info/RECORD
