Metadata-Version: 2.1
Name: trplearn
Version: 0.1.1
Summary: tropical-based calculation
Author: iskzhi
License: MIT License
Project-URL: Documentation, https://iskzhi.github.io/trplearn/index.html
Project-URL: Repository, https://github.com/iskzhi/trplearn
Classifier: Development Status :: 3 - Alpha
Classifier: License :: OSI Approved :: MIT License
Classifier: Programming Language :: Python :: 3
Requires-Python: >=3.10
License-File: LICENSE
Requires-Dist: numpy
Provides-Extra: dev
Requires-Dist: build ; extra == 'dev'
Requires-Dist: twine ; extra == 'dev'
